README.rst
setup.py
parallel_phpunit.egg-info/PKG-INFO
parallel_phpunit.egg-info/SOURCES.txt
parallel_phpunit.egg-info/dependency_links.txt
parallel_phpunit.egg-info/entry_points.txt
parallel_phpunit.egg-info/not-zip-safe
parallel_phpunit.egg-info/top_level.txt
parallelphpunit/__init__.py
parallelphpunit/files.py
parallelphpunit/runner.py
parallelphpunit/suite.py