Metadata-Version: 1.0
Name: parallel-phpunit
Version: 1.0.0
Summary: Parallel Test Cases Runner for PHPUnit
Home-page: https://github.com/socialpoint/parallel-phpunit
Author: Felix Carmona
Author-email: UNKNOWN
License: UNKNOWN
Platform: UNKNOWN
